odoo/addons/account_multicurrency_revaluation_rate_type/README.rst
odoo/addons/account_multicurrency_revaluation_rate_type/__init__.py
odoo/addons/account_multicurrency_revaluation_rate_type/__manifest__.py
odoo/addons/account_multicurrency_revaluation_rate_type/i18n/account_multicurrency_revaluation_rate_type.pot
odoo/addons/account_multicurrency_revaluation_rate_type/i18n/fr_FR.po
odoo/addons/account_multicurrency_revaluation_rate_type/i18n/pt.po
odoo/addons/account_multicurrency_revaluation_rate_type/i18n/pt_BR.po
odoo/addons/account_multicurrency_revaluation_rate_type/models/__init__.py
odoo/addons/account_multicurrency_revaluation_rate_type/models/res_company.py
odoo/addons/account_multicurrency_revaluation_rate_type/models/res_config.py
odoo/addons/account_multicurrency_revaluation_rate_type/readme/CONTRIBUTORS.rst
odoo/addons/account_multicurrency_revaluation_rate_type/readme/DESCRIPTION.rst
odoo/addons/account_multicurrency_revaluation_rate_type/static/description/icon.png
odoo/addons/account_multicurrency_revaluation_rate_type/static/description/index.html
odoo/addons/account_multicurrency_revaluation_rate_type/tests/__init__.py
odoo/addons/account_multicurrency_revaluation_rate_type/tests/test_currency_revaluation.py
odoo/addons/account_multicurrency_revaluation_rate_type/views/res_config_view.xml
odoo/addons/account_multicurrency_revaluation_rate_type/wizard/__init__.py
odoo/addons/account_multicurrency_revaluation_rate_type/wizard/wizard_currency_revaluation.py
odoo/addons/account_multicurrency_revaluation_rate_type/wizard/wizard_currency_revaluation_view.xml
odoo12_addon_account_multicurrency_revaluation_rate_type-12.0.1.0.3.dist-info/METADATA
odoo12_addon_account_multicurrency_revaluation_rate_type-12.0.1.0.3.dist-info/WHEEL
odoo12_addon_account_multicurrency_revaluation_rate_type-12.0.1.0.3.dist-info/top_level.txt
odoo12_addon_account_multicurrency_revaluation_rate_type-12.0.1.0.3.dist-info/RECORD
